.flake8
LICENSE
MANIFEST.in
README.md
pyproject.toml
requirements.txt
setup.cfg
setup.py
flask_vault/__init__.py
flask_vault/cli.py
flask_vault/utils.py
flask_vault/lib/__init__.py
flask_vault/lib/secrets.py
flask_vault/lib/cryptography/__init__.py
flask_vault/lib/cryptography/aes.py