Metadata-Version: 2.1
Name: Flask-Vault
Version: 0.2.0
Summary: Secure Credential Storage for Flask
Home-page: https://github.com/multiversecoder/Flask-Vault
Author: Adriano Romanazzo (multiversecoder)
Author-email: pythonmultiverse@gmx.com
License: MIT License
Project-URL: Issue Tracker, https://github.com/multiversecoder/Flask-Vault/issues
Keywords: Flask,Flask-Vault,Flask Vault,Flask Credentials,AES GCM Encryption,Flask AES
Classifier: Development Status :: 5 - Production/Stable
Classifier: Environment :: Console
Classifier: License :: OSI Approved :: MIT License
Classifier: Intended Audience :: Developers
Classifier: Programming Language :: Python
Classifier: Programming Language :: Python :: 3
Classifier: Programming Language :: Python :: 3.7
Classifier: Programming Language :: Python :: 3.8
Classifier: Programming Language :: Python :: 3.9
Classifier: Programming Language :: Python :: 3.10
Classifier: Programming Language :: Python :: 3.11
Classifier: Programming Language :: Python :: Implementation :: CPython
Requires-Python: !=3.0.*, !=3.1.*, !=3.2.*, !=3.3.*
License-File: LICENSE
